README
setup.py
pastegevent/__init__.py
pastegevent/server.py
pastegevent.egg-info/PKG-INFO
pastegevent.egg-info/SOURCES.txt
pastegevent.egg-info/dependency_links.txt
pastegevent.egg-info/entry_points.txt
pastegevent.egg-info/requires.txt
pastegevent.egg-info/top_level.txt
pastegevent.egg-info/zip-safe