Metadata-Version: 1.0
Name: pastegevent
Version: 0.1
Summary: Run WSGI applications with PasteDeploy and gevent.
Home-page: UNKNOWN
Author: Andrey Popp
Author-email: 8mayday@gmail.com
License: MIT
Keywords: paste wsgi gevent
Platform: UNKNOWN
Classifier: Environment :: Plugins
Classifier: Framework :: Paste
Classifier: Intended Audience :: Developers
Classifier: License :: OSI Approved :: MIT License
Classifier: Operating System :: OS Independent
Classifier: Programming Language :: Python
Classifier: Topic :: Internet :: WWW/HTTP :: HTTP Servers
